{
    "outputlayer": [
        {
            "neurons": [
                {
                    "bias": "-0.857619", 
                    "weights": [
                        "-11.439", 
                        "-6.4723"
                    ], 
                    "id": 1
                }, 
                {
                    "bias": "-11.2794", 
                    "weights": [
                        "16.2144", 
                        "-3.28241"
                    ], 
                    "id": 2
                }, 
                {
                    "bias": "0.848852", 
                    "weights": [
                        "-10.6376", 
                        "-38.8971"
                    ], 
                    "id": 2
                }, 
                {
                    "bias": "-9.70371", 
                    "weights": [
                        "-17.8564", 
                        "9.49117"
                    ], 
                    "id": 3
                }
            ]
        }
    ]
}